tarpan/__init__.py
tarpan/cmdstanpy/__init__.py
tarpan/cmdstanpy/analyse.py
tarpan/cmdstanpy/analyse_test.py
tarpan/cmdstanpy/cache.py
tarpan/cmdstanpy/cache_test.py
tarpan/cmdstanpy/compare.py
tarpan/cmdstanpy/compare_parameters.py
tarpan/cmdstanpy/compare_parameters_test.py
tarpan/cmdstanpy/compare_test.py
tarpan/cmdstanpy/histogram.py
tarpan/cmdstanpy/histogram_test.py
tarpan/cmdstanpy/pair_plot.py
tarpan/cmdstanpy/pair_plot_test.py
tarpan/cmdstanpy/psis.py
tarpan/cmdstanpy/psis_from_arviz.py
tarpan/cmdstanpy/psis_test.py
tarpan/cmdstanpy/summary.py
tarpan/cmdstanpy/summary_test.py
tarpan/cmdstanpy/traceplot.py
tarpan/cmdstanpy/traceplot_test.py
tarpan/cmdstanpy/tree_plot.py
tarpan/cmdstanpy/tree_plot_test.py
tarpan/cmdstanpy/waic.py
tarpan/cmdstanpy/waic_test.py
tarpan/plot/__init__.py
tarpan/plot/kde.py
tarpan/plot/kde_test.py
tarpan/plot/posterior.py
tarpan/plot/posterior_test.py
tarpan/plot/utils.py
tarpan/shared/__init__.py
tarpan/shared/analyse.py
tarpan/shared/analyse_test.py
tarpan/shared/compare.py
tarpan/shared/compare_parameters.py
tarpan/shared/compare_parameters_test.py
tarpan/shared/compare_test.py
tarpan/shared/histogram.py
tarpan/shared/histogram_test.py
tarpan/shared/info_path.py
tarpan/shared/info_path_test.py
tarpan/shared/pair_plot.py
tarpan/shared/pair_plot_test.py
tarpan/shared/param_names.py
tarpan/shared/param_names_test.py
tarpan/shared/stats.py
tarpan/shared/stats_test.py
tarpan/shared/summary.py
tarpan/shared/summary_test.py
tarpan/shared/tree_plot.py
tarpan/shared/tree_plot_test.py
tarpan-0.3.11.dist-info/LICENSE
tarpan-0.3.11.dist-info/METADATA
tarpan-0.3.11.dist-info/WHEEL
tarpan-0.3.11.dist-info/top_level.txt
tarpan-0.3.11.dist-info/RECORD
