Metadata-Version: 2.1
Name: tarpan
Version: 0.3.11
Summary: A collection of tools for analysing cmdspanpy output, written in Python
Home-page: https://github.com/evgenyneu/tarpan
Author: Evgenii Neumerzhitckii
Author-email: sausageskin@gmail.com
License: Public Domain
Platform: UNKNOWN
Classifier: Programming Language :: Python :: 3
Classifier: License :: Public Domain
Classifier: Operating System :: OS Independent
Requires-Python: >=3.7
Requires-Dist: cmdstanpy (<0.9.3,>=0.9.2)
Requires-Dist: scipy (<2.0.0,>=1.4.1)
Requires-Dist: tabulate (<0.9.0,>=0.8.6)
Requires-Dist: pandas (<0.26.0,>=0.25.3)
Requires-Dist: numpy (<1.18.2,>=1.18.1)
Requires-Dist: matplotlib (<4.0.0,>=3.1.2)
Requires-Dist: seaborn (<0.11.0,>=0.10.0)
